README.md
setup.cfg
setup.py
monypy/__init__.py
monypy/doc.py
monypy/exceptions.py
monypy/helpers.py
monypy/manager.py
monypy/meta.py
monypy.egg-info/PKG-INFO
monypy.egg-info/SOURCES.txt
monypy.egg-info/dependency_links.txt
monypy.egg-info/requires.txt
monypy.egg-info/top_level.txt