Metadata-Version: 2.1
Name: monypy
Version: 2.0
Summary: Asynchronous lightweight ODM for mongodb based on motor
Home-page: http://github.com/nede1/monypy
Author: Yaroslav Unknown
Author-email: yaroslav@gmx.it
License: MIT
Keywords: asyncio mongodb motor odm
Platform: UNKNOWN
Classifier: Development Status :: 3 - Alpha
Classifier: Framework :: AsyncIO
Classifier: License :: OSI Approved :: MIT License
Classifier: Programming Language :: Python :: 3.7
Classifier: Topic :: Software Development
Classifier: Topic :: Software Development :: Libraries
